{
  "id": "24f1782f-7e4b-4555-9a08-78f38c7f4fe1",
  "realm": "forum",
  "notBefore": 0,
  "defaultSignatureAlgorithm": "RS256",
  "revokeRefreshToken": false,
  "refreshTokenMaxReuse": 0,
  "accessTokenLifespan": 300,
  "accessTokenLifespanForImplicitFlow": 900,
  "ssoSessionIdleTimeout": 1800,
  "ssoSessionMaxLifespan": 36000,
  "ssoSessionIdleTimeoutRememberMe": 0,
  "ssoSessionMaxLifespanRememberMe": 0,
  "offlineSessionIdleTimeout": 2592000,
  "offlineSessionMaxLifespanEnabled": false,
  "offlineSessionMaxLifespan": 5184000,
  "clientSessionIdleTimeout": 0,
  "clientSessionMaxLifespan": 0,
  "clientOfflineSessionIdleTimeout": 0,
  "clientOfflineSessionMaxLifespan": 0,
  "accessCodeLifespan": 60,
  "accessCodeLifespanUserAction": 300,
  "accessCodeLifespanLogin": 1800,
  "actionTokenGeneratedByAdminLifespan": 43200,
  "actionTokenGeneratedByUserLifespan": 300,
  "oauth2DeviceCodeLifespan": 600,
  "oauth2DevicePollingInterval": 5,
  "enabled": true,
  "sslRequired": "external",
  "registrationAllowed": false,
  "registrationEmailAsUsername": false,
  "rememberMe": false,
  "verifyEmail": false,
  "loginWithEmailAllowed": true,
  "duplicateEmailsAllowed": false,
  "resetPasswordAllowed": false,
  "editUsernameAllowed": false,
  "bruteForceProtected": false,
  "permanentLockout": false,
  "maxTemporaryLockouts": 0,
  "bruteForceStrategy": "MULTIPLE",
  "maxFailureWaitSeconds": 900,
  "minimumQuickLoginWaitSeconds": 60,
  "waitIncrementSeconds": 60,
  "quickLoginCheckMilliSeconds": 1000,
  "maxDeltaTimeSeconds": 43200,
  "failureFactor": 30,
  "roles": {
    "realm": [
      {
        "id": "02815bab-1a63-46ad-b17a-302fca0a2086",
        "name": "default-roles-forum",
        "description": "${role_default-roles}",
        "composite": true,
        "composites": {
          "realm": [
            "offline_access",
            "uma_authorization"
          ],
          "client": {
            "account": [
              "manage-account",
              "view-profile"
            ]
          }
        },
        "clientRole": false,
        "containerId": "24f1782f-7e4b-4555-9a08-78f38c7f4fe1",
        "attributes": {}
      },
      {
        "id": "5d07aef5-d479-4636-ade7-165b93fdf9c7",
        "name": "user",
        "description": "User role",
        "composite": true,
        "composites": {
          "client": {
            "public-client": [
              "client_user"
            ]
          }
        },
        "clientRole": false,
        "containerId": "24f1782f-7e4b-4555-9a08-78f38c7f4fe1",
        "attributes": {}
      },
      {
        "id": "f73163b8-ad19-44a5-af65-a6bfbd1a4bf8",
        "name": "uma_authorization",
        "description": "${role_uma_authorization}",
        "composite": false,
        "clientRole": false,
        "containerId": "24f1782f-7e4b-4555-9a08-78f38c7f4fe1",
        "attributes": {}
      },
      {
        "id": "e9bcdede-570e-4447-8e91-c07820514850",
        "name": "admin",
        "description": "Admin role",
        "composite": true,
        "composites": {
          "client": {
            "public-client": [
              "client_admin"
            ]
          }
        },
        "clientRole": false,
        "containerId": "24f1782f-7e4b-4555-9a08-78f38c7f4fe1",
        "attributes": {}
      },
      {
        "id": "37603308-3bf5-4644-ab46-185f3d4ee4ed",
        "name": "offline_access",
        "description": "${role_offline-access}",
        "composite": false,
        "clientRole": false,
        "containerId": "24f1782f-7e4b-4555-9a08-78f38c7f4fe1",
        "attributes": {}
      }
    ],
    "client": {
      "realm-management": [
        {
          "id": "d97632fd-d61d-4ec6-849b-620cffe06583",
          "name": "view-events",
          "description": "${role_view-events}",
          "composite": false,
          "clientRole": true,
          "containerId": "fb33a45c-776d-4205-a318-08e231d96356",
          "attributes": {}
        },
        {
          "id": "45214c9a-69bd-470c-ae6f-3b199dae61c6",
          "name": "view-users",
          "description": "${role_view-users}",
          "composite": true,
          "composites": {
            "client": {
              "realm-management": [
                "query-users",
                "query-groups"
              ]
            }
          },
          "clientRole": true,
          "containerId": "fb33a45c-776d-4205-a318-08e231d96356",
          "attributes": {}
        },
        {
          "id": "8022ce15-3912-4bca-9e28-110c1ce43611",
          "name": "manage-users",
          "description": "${role_manage-users}",
          "composite": false,
          "clientRole": true,
          "containerId": "fb33a45c-776d-4205-a318-08e231d96356",
          "attributes": {}
        },
        {
          "id": "8067e88f-da0c-431b-b5fd-ba0ffceed840",
          "name": "view-identity-providers",
          "description": "${role_view-identity-providers}",
          "composite": false,
          "clientRole": true,
          "containerId": "fb33a45c-776d-4205-a318-08e231d96356",
          "attributes": {}
        },
        {
          "id": "0e733942-f647-4227-b05e-60b2a969e934",
          "name": "query-clients",
          "description": "${role_query-clients}",
          "composite": false,
          "clientRole": true,
          "containerId": "fb33a45c-776d-4205-a318-08e231d96356",
          "attributes": {}
        },
        {
          "id": "cc4eafbc-4351-4985-855d-b3fb85125778",
          "name": "query-users",
          "description": "${role_query-users}",
          "composite": false,
          "clientRole": true,
          "containerId": "fb33a45c-776d-4205-a318-08e231d96356",
          "attributes": {}
        },
        {
          "id": "c2cb61f7-e115-49c4-8967-4be340d88add",
          "name": "manage-realm",
          "description": "${role_manage-realm}",
          "composite": false,
          "clientRole": true,
          "containerId": "fb33a45c-776d-4205-a318-08e231d96356",
          "attributes": {}
        },
        {
          "id": "eeec64a1-a252-4d30-937f-55974b8005a9",
          "name": "view-realm",
          "description": "${role_view-realm}",
          "composite": false,
          "clientRole": true,
          "containerId": "fb33a45c-776d-4205-a318-08e231d96356",
          "attributes": {}
        },
        {
          "id": "7f8226da-f7a1-487f-8a0f-ddb6a97d320a",
          "name": "query-groups",
          "description": "${role_query-groups}",
          "composite": false,
          "clientRole": true,
          "containerId": "fb33a45c-776d-4205-a318-08e231d96356",
          "attributes": {}
        },
        {
          "id": "ea7c5ebf-0196-467c-a740-ee9a58ee109f",
          "name": "realm-admin",
          "description": "${role_realm-admin}",
          "composite": true,
          "composites": {
            "client": {
              "realm-management": [
                "view-users",
                "view-events",
                "view-identity-providers",
                "manage-users",
                "query-users",
                "query-clients",
                "view-realm",
                "manage-realm",
                "query-groups",
                "manage-clients",
                "view-authorization",
                "query-realms",
                "impersonation",
                "manage-events",
                "create-client",
                "manage-authorization",
                "view-clients",
                "manage-identity-providers"
              ]
            }
          },
          "clientRole": true,
          "containerId": "fb33a45c-776d-4205-a318-08e231d96356",
          "attributes": {}
        },
        {
          "id": "5a4c83ea-7908-4200-baac-48419aaa0013",
          "name": "manage-clients",
          "description": "${role_manage-clients}",
          "composite": false,
          "clientRole": true,
          "containerId": "fb33a45c-776d-4205-a318-08e231d96356",
          "attributes": {}
        },
        {
          "id": "787283c6-2f12-4add-9335-936d47070804",
          "name": "query-realms",
          "description": "${role_query-realms}",
          "composite": false,
          "clientRole": true,
          "containerId": "fb33a45c-776d-4205-a318-08e231d96356",
          "attributes": {}
        },
        {
          "id": "43ad258f-bc42-4c1d-86c4-d934d16bd22c",
          "name": "view-authorization",
          "description": "${role_view-authorization}",
          "composite": false,
          "clientRole": true,
          "containerId": "fb33a45c-776d-4205-a318-08e231d96356",
          "attributes": {}
        },
        {
          "id": "99034d1a-658e-4a7e-9d53-a01994b088ce",
          "name": "impersonation",
          "description": "${role_impersonation}",
          "composite": false,
          "clientRole": true,
          "containerId": "fb33a45c-776d-4205-a318-08e231d96356",
          "attributes": {}
        },
        {
          "id": "18131e91-fb8b-4941-8791-c402cc0b006d",
          "name": "manage-events",
          "description": "${role_manage-events}",
          "composite": false,
          "clientRole": true,
          "containerId": "fb33a45c-776d-4205-a318-08e231d96356",
          "attributes": {}
        },
        {
          "id": "4d0bfeae-0b6f-4d36-becb-4aad1eb3c206",
          "name": "create-client",
          "description": "${role_create-client}",
          "composite": false,
          "clientRole": true,
          "containerId": "fb33a45c-776d-4205-a318-08e231d96356",
          "attributes": {}
        },
        {
          "id": "a46a2034-3932-4822-a1e9-c8a43184ff3e",
          "name": "manage-authorization",
          "description": "${role_manage-authorization}",
          "composite": false,
          "clientRole": true,
          "containerId": "fb33a45c-776d-4205-a318-08e231d96356",
          "attributes": {}
        },
        {
          "id": "33b58147-be3e-4214-8004-afcce6929e8c",
          "name": "view-clients",
          "description": "${role_view-clients}",
          "composite": true,
          "composites": {
            "client": {
              "realm-management": [
                "query-clients"
              ]
            }
          },
          "clientRole": true,
          "containerId": "fb33a45c-776d-4205-a318-08e231d96356",
          "attributes": {}
        },
        {
          "id": "ac85fafa-0fd9-411f-897c-31e58e601d74",
          "name": "manage-identity-providers",
          "description": "${role_manage-identity-providers}",
          "composite": false,
          "clientRole": true,
          "containerId": "fb33a45c-776d-4205-a318-08e231d96356",
          "attributes": {}
        }
      ],
      "public-client": [
        {
          "id": "fa4b89d3-d892-4d3f-9b34-a8be48ca5e42",
          "name": "client_user",
          "description": "Client user",
          "composite": false,
          "clientRole": true,
          "containerId": "55a31f2a-c5d1-4a95-a216-83acf5b372e2",
          "attributes": {}
        },
        {
          "id": "c51ef783-efe3-4a50-9e2b-3e03fa8b6da3",
          "name": "client_admin",
          "description": "Client admin",
          "composite": false,
          "clientRole": true,
          "containerId": "55a31f2a-c5d1-4a95-a216-83acf5b372e2",
          "attributes": {}
        }
      ],
      "security-admin-console": [],
      "admin-cli": [],
      "account-console": [],
      "broker": [
        {
          "id": "913f8e38-7438-4441-843c-608451599f77",
          "name": "read-token",
          "description": "${role_read-token}",
          "composite": false,
          "clientRole": true,
          "containerId": "1c2c1c54-d8fd-448e-ba96-2115ae5e3a99",
          "attributes": {}
        }
      ],
      "account": [
        {
          "id": "734797d6-bcb0-4809-a01b-5e8b9f1b7d10",
          "name": "view-consent",
          "description": "${role_view-consent}",
          "composite": false,
          "clientRole": true,
          "containerId": "9139e8bb-6933-4c0a-83aa-ee25e7981a24",
          "attributes": {}
        },
        {
          "id": "c3471f71-0c5a-4b5e-8d20-30d7597e09a3",
          "name": "manage-consent",
          "description": "${role_manage-consent}",
          "composite": true,
          "composites": {
            "client": {
              "account": [
                "view-consent"
              ]
            }
          },
          "clientRole": true,
          "containerId": "9139e8bb-6933-4c0a-83aa-ee25e7981a24",
          "attributes": {}
        },
        {
          "id": "5eb77319-4279-4923-9ef0-f35fb7134c64",
          "name": "manage-account-links",
          "description": "${role_manage-account-links}",
          "composite": false,
          "clientRole": true,
          "containerId": "9139e8bb-6933-4c0a-83aa-ee25e7981a24",
          "attributes": {}
        },
        {
          "id": "e7eaeac3-a41e-42c8-a6c3-391242038760",
          "name": "manage-account",
          "description": "${role_manage-account}",
          "composite": true,
          "composites": {
            "client": {
              "account": [
                "manage-account-links"
              ]
            }
          },
          "clientRole": true,
          "containerId": "9139e8bb-6933-4c0a-83aa-ee25e7981a24",
          "attributes": {}
        },
        {
          "id": "d7a6d0e1-2ed2-45c3-bb9d-0d2855b7abd1",
          "name": "view-profile",
          "description": "${role_view-profile}",
          "composite": false,
          "clientRole": true,
          "containerId": "9139e8bb-6933-4c0a-83aa-ee25e7981a24",
          "attributes": {}
        },
        {
          "id": "c8080e12-835a-41ca-930c-cab82b35529e",
          "name": "delete-account",
          "description": "${role_delete-account}",
          "composite": false,
          "clientRole": true,
          "containerId": "9139e8bb-6933-4c0a-83aa-ee25e7981a24",
          "attributes": {}
        },
        {
          "id": "e3a03ddd-1e47-49c5-86ee-af8a659e27be",
          "name": "view-applications",
          "description": "${role_view-applications}",
          "composite": false,
          "clientRole": true,
          "containerId": "9139e8bb-6933-4c0a-83aa-ee25e7981a24",
          "attributes": {}
        },
        {
          "id": "aa9fa82c-5e9e-4f03-ba12-0a82fd84c3c0",
          "name": "view-groups",
          "description": "${role_view-groups}",
          "composite": false,
          "clientRole": true,
          "containerId": "9139e8bb-6933-4c0a-83aa-ee25e7981a24",
          "attributes": {}
        }
      ]
    }
  },
  "groups": [],
  "defaultRole": {
    "id": "02815bab-1a63-46ad-b17a-302fca0a2086",
    "name": "default-roles-forum",
    "description": "${role_default-roles}",
    "composite": true,
    "clientRole": false,
    "containerId": "24f1782f-7e4b-4555-9a08-78f38c7f4fe1"
  },
  "requiredCredentials": [
    "password"
  ],
  "otpPolicyType": "totp",
  "otpPolicyAlgorithm": "HmacSHA1",
  "otpPolicyInitialCounter": 0,
  "otpPolicyDigits": 6,
  "otpPolicyLookAheadWindow": 1,
  "otpPolicyPeriod": 30,
  "otpPolicyCodeReusable": false,
  "otpSupportedApplications": [
    "totpAppFreeOTPName",
    "totpAppGoogleName",
    "totpAppMicrosoftAuthenticatorName"
  ],
  "localizationTexts": {},
  "webAuthnPolicyRpEntityName": "keycloak",
  "webAuthnPolicySignatureAlgorithms": [
    "ES256",
    "RS256"
  ],
  "webAuthnPolicyRpId": "",
  "webAuthnPolicyAttestationConveyancePreference": "not specified",
  "webAuthnPolicyAuthenticatorAttachment": "not specified",
  "webAuthnPolicyRequireResidentKey": "not specified",
  "webAuthnPolicyUserVerificationRequirement": "not specified",
  "webAuthnPolicyCreateTimeout": 0,
  "webAuthnPolicyAvoidSameAuthenticatorRegister": false,
  "webAuthnPolicyAcceptableAaguids": [],
  "webAuthnPolicyExtraOrigins": [],
  "webAuthnPolicyPasswordlessRpEntityName": "keycloak",
  "webAuthnPolicyPasswordlessSignatureAlgorithms": [
    "ES256",
    "RS256"
  ],
  "webAuthnPolicyPasswordlessRpId": "",
  "webAuthnPolicyPasswordlessAttestationConveyancePreference": "not specified",
  "webAuthnPolicyPasswordlessAuthenticatorAttachment": "not specified",
  "webAuthnPolicyPasswordlessRequireResidentKey": "not specified",
  "webAuthnPolicyPasswordlessUserVerificationRequirement": "not specified",
  "webAuthnPolicyPasswordlessCreateTimeout": 0,
  "webAuthnPolicyPasswordlessAvoidSameAuthenticatorRegister": false,
  "webAuthnPolicyPasswordlessAcceptableAaguids": [],
  "webAuthnPolicyPasswordlessExtraOrigins": [],
  "scopeMappings": [
    {
      "clientScope": "offline_access",
      "roles": [
        "offline_access"
      ]
    }
  ],
  "clientScopeMappings": {
    "account": [
      {
        "client": "account-console",
        "roles": [
          "manage-account",
          "view-groups"
        ]
      }
    ]
  },
  "clients": [
    {
      "id": "9139e8bb-6933-4c0a-83aa-ee25e7981a24",
      "clientId": "account",
      "name": "${client_account}",
      "rootUrl": "${authBaseUrl}",
      "baseUrl": "/realms/forum/account/",
      "surrogateAuthRequired": false,
      "enabled": true,
      "alwaysDisplayInConsole": false,
      "clientAuthenticatorType": "client-secret",
      "redirectUris": [
        "/realms/forum/account/*"
      ],
      "webOrigins": [],
      "notBefore": 0,
      "bearerOnly": false,
      "consentRequired": false,
      "standardFlowEnabled": true,
      "implicitFlowEnabled": false,
      "directAccessGrantsEnabled": false,
      "serviceAccountsEnabled": false,
      "publicClient": true,
      "frontchannelLogout": false,
      "protocol": "openid-connect",
      "attributes": {
        "realm_client": "false",
        "post.logout.redirect.uris": "+"
      },
      "authenticationFlowBindingOverrides": {},
      "fullScopeAllowed": false,
      "nodeReRegistrationTimeout": 0,
      "defaultClientScopes": [
        "web-origins",
        "acr",
        "roles",
        "profile",
        "basic",
        "email"
      ],
      "optionalClientScopes": [
        "address",
        "phone",
        "organization",
        "offline_access",
        "microprofile-jwt"
      ]
    },
    {
      "id": "fe5cbe48-3b62-490b-b798-a455e2e10116",
      "clientId": "account-console",
      "name": "${client_account-console}",
      "rootUrl": "${authBaseUrl}",
      "baseUrl": "/realms/forum/account/",
      "surrogateAuthRequired": false,
      "enabled": true,
      "alwaysDisplayInConsole": false,
      "clientAuthenticatorType": "client-secret",
      "redirectUris": [
        "/realms/forum/account/*"
      ],
      "webOrigins": [],
      "notBefore": 0,
      "bearerOnly": false,
      "consentRequired": false,
      "standardFlowEnabled": true,
      "implicitFlowEnabled": false,
      "directAccessGrantsEnabled": false,
      "serviceAccountsEnabled": false,
      "publicClient": true,
      "frontchannelLogout": false,
      "protocol": "openid-connect",
      "attributes": {
        "realm_client": "false",
        "post.logout.redirect.uris": "+",
        "pkce.code.challenge.method": "S256"
      },
      "authenticationFlowBindingOverrides": {},
      "fullScopeAllowed": false,
      "nodeReRegistrationTimeout": 0,
      "protocolMappers": [
        {
          "id": "b063d732-7f13-46a6-8a21-789f5f632c28",
          "name": "audience resolve",
          "protocol": "openid-connect",
          "protocolMapper": "oidc-audience-resolve-mapper",
          "consentRequired": false,
          "config": {}
        }
      ],
      "defaultClientScopes": [
        "web-origins",
        "acr",
        "roles",
        "profile",
        "basic",
        "email"
      ],
      "optionalClientScopes": [
        "address",
        "phone",
        "organization",
        "offline_access",
        "microprofile-jwt"
      ]
    },
    {
      "id": "11369391-fe83-4eb9-b3ff-897333a48cf1",
      "clientId": "admin-cli",
      "name": "${client_admin-cli}",
      "surrogateAuthRequired": false,
      "enabled": true,
      "alwaysDisplayInConsole": false,
      "clientAuthenticatorType": "client-secret",
      "redirectUris": [],
      "webOrigins": [],
      "notBefore": 0,
      "bearerOnly": false,
      "consentRequired": false,
      "standardFlowEnabled": false,
      "implicitFlowEnabled": false,
      "directAccessGrantsEnabled": true,
      "serviceAccountsEnabled": false,
      "publicClient": true,
      "frontchannelLogout": false,
      "protocol": "openid-connect",
      "attributes": {
        "realm_client": "false",
        "client.use.lightweight.access.token.enabled": "true"
      },
      "authenticationFlowBindingOverrides": {},
      "fullScopeAllowed": true,
      "nodeReRegistrationTimeout": 0,
      "defaultClientScopes": [
        "web-origins",
        "acr",
        "roles",
        "profile",
        "basic",
        "email"
      ],
      "optionalClientScopes": [
        "address",
        "phone",
        "organization",
        "offline_access",
        "microprofile-jwt"
      ]
    },
    {
      "id": "1c2c1c54-d8fd-448e-ba96-2115ae5e3a99",
      "clientId": "broker",
      "name": "${client_broker}",
      "surrogateAuthRequired": false,
      "enabled": true,
      "alwaysDisplayInConsole": false,
      "clientAuthenticatorType": "client-secret",
      "redirectUris": [],
      "webOrigins": [],
      "notBefore": 0,
      "bearerOnly": true,
      "consentRequired": false,
      "standardFlowEnabled": true,
      "implicitFlowEnabled": false,
      "directAccessGrantsEnabled": false,
      "serviceAccountsEnabled": false,
      "publicClient": false,
      "frontchannelLogout": false,
      "protocol": "openid-connect",
      "attributes": {
        "realm_client": "true"
      },
      "authenticationFlowBindingOverrides": {},
      "fullScopeAllowed": false,
      "nodeReRegistrationTimeout": 0,
      "defaultClientScopes": [
        "web-origins",
        "acr",
        "roles",
        "profile",
        "basic",
        "email"
      ],
      "optionalClientScopes": [
        "address",
        "phone",
        "organization",
        "offline_access",
        "microprofile-jwt"
      ]
    },
    {
      "id": "55a31f2a-c5d1-4a95-a216-83acf5b372e2",
      "clientId": "public-client",
      "name": "public cient",
      "description": "react forum public client",
      "rootUrl": "http://localhost:8080",
      "adminUrl": "http://localhost:8080",
      "baseUrl": "http://localhost:8080",
      "surrogateAuthRequired": false,
      "enabled": true,
      "alwaysDisplayInConsole": false,
      "clientAuthenticatorType": "client-secret",
      "redirectUris": [
        "http://localhost:8080/*"
      ],
      "webOrigins": [
        "*"
      ],
      "notBefore": 0,
      "bearerOnly": false,
      "consentRequired": false,
      "standardFlowEnabled": true,
      "implicitFlowEnabled": false,
      "directAccessGrantsEnabled": true,
      "serviceAccountsEnabled": false,
      "publicClient": true,
      "frontchannelLogout": true,
      "protocol": "openid-connect",
      "attributes": {
        "realm_client": "false",
        "oidc.ciba.grant.enabled": "false",
        "backchannel.logout.session.required": "true",
        "post.logout.redirect.uris": "http://localhost:8080",
        "display.on.consent.screen": "false",
        "oauth2.device.authorization.grant.enabled": "false",
        "backchannel.logout.revoke.offline.tokens": "false"
      },
      "authenticationFlowBindingOverrides": {},
      "fullScopeAllowed": true,
      "nodeReRegistrationTimeout": -1,
      "defaultClientScopes": [
        "web-origins",
        "acr",
        "roles",
        "profile",
        "basic",
        "email"
      ],
      "optionalClientScopes": [
        "address",
        "phone",
        "organization",
        "offline_access",
        "microprofile-jwt"
      ]
    },
    {
      "id": "fb33a45c-776d-4205-a318-08e231d96356",
      "clientId": "realm-management",
      "name": "${client_realm-management}",
      "surrogateAuthRequired": false,
      "enabled": true,
      "alwaysDisplayInConsole": false,
      "clientAuthenticatorType": "client-secret",
      "redirectUris": [],
      "webOrigins": [],
      "notBefore": 0,
      "bearerOnly": true,
      "consentRequired": false,
      "standardFlowEnabled": true,
      "implicitFlowEnabled": false,
      "directAccessGrantsEnabled": false,
      "serviceAccountsEnabled": false,
      "publicClient": false,
      "frontchannelLogout": false,
      "protocol": "openid-connect",
      "attributes": {
        "realm_client": "true"
      },
      "authenticationFlowBindingOverrides": {},
      "fullScopeAllowed": false,
      "nodeReRegistrationTimeout": 0,
      "defaultClientScopes": [
        "web-origins",
        "acr",
        "roles",
        "profile",
        "basic",
        "email"
      ],
      "optionalClientScopes": [
        "address",
        "phone",
        "organization",
        "offline_access",
        "microprofile-jwt"
      ]
    },
    {
      "id": "4ae2787d-52e6-403e-9c89-305a9431ab47",
      "clientId": "security-admin-console",
      "name": "${client_security-admin-console}",
      "rootUrl": "${authAdminUrl}",
      "baseUrl": "/admin/forum/console/",
      "surrogateAuthRequired": false,
      "enabled": true,
      "alwaysDisplayInConsole": false,
      "clientAuthenticatorType": "client-secret",
      "redirectUris": [
        "/admin/forum/console/*"
      ],
      "webOrigins": [
        "+"
      ],
      "notBefore": 0,
      "bearerOnly": false,
      "consentRequired": false,
      "standardFlowEnabled": true,
      "implicitFlowEnabled": false,
      "directAccessGrantsEnabled": false,
      "serviceAccountsEnabled": false,
      "publicClient": true,
      "frontchannelLogout": false,
      "protocol": "openid-connect",
      "attributes": {
        "realm_client": "false",
        "client.use.lightweight.access.token.enabled": "true",
        "post.logout.redirect.uris": "+",
        "pkce.code.challenge.method": "S256"
      },
      "authenticationFlowBindingOverrides": {},
      "fullScopeAllowed": true,
      "nodeReRegistrationTimeout": 0,
      "protocolMappers": [
        {
          "id": "adfe9734-f4b7-4ed2-98ff-83d85ea23984",
          "name": "locale",
          "protocol": "openid-connect",
          "protocolMapper": "oidc-usermodel-attribute-mapper",
          "consentRequired": false,
          "config": {
            "introspection.token.claim": "true",
            "userinfo.token.claim": "true",
            "user.attribute": "locale",
            "id.token.claim": "true",
            "access.token.claim": "true",
            "claim.name": "locale",
            "jsonType.label": "String"
          }
        }
      ],
      "defaultClientScopes": [
        "web-origins",
        "acr",
        "roles",
        "profile",
        "basic",
        "email"
      ],
      "optionalClientScopes": [
        "address",
        "phone",
        "organization",
        "offline_access",
        "microprofile-jwt"
      ]
    }
  ],
  "clientScopes": [
    {
      "id": "af45bf5a-4d4c-400f-ba6e-c22d9d6df0d5",
      "name": "profile",
      "description": "OpenID Connect built-in scope: profile",
      "protocol": "openid-connect",
      "attributes": {
        "include.in.token.scope": "true",
        "consent.screen.text": "${profileScopeConsentText}",
        "display.on.consent.screen": "true"
      },
      "protocolMappers": [
        {
          "id": "ae166676-35fe-4cb7-880f-c75c52ce33c9",
          "name": "picture",
          "protocol": "openid-connect",
          "protocolMapper": "oidc-usermodel-attribute-mapper",
          "consentRequired": false,
          "config": {
            "introspection.token.claim": "true",
            "userinfo.token.claim": "true",
            "user.attribute": "picture",
            "id.token.claim": "true",
            "access.token.claim": "true",
            "claim.name": "picture",
            "jsonType.label": "String"
          }
        },
        {
          "id": "367a4dac-c0b9-4a40-a14c-f142ae165656",
          "name": "profile",
          "protocol": "openid-connect",
          "protocolMapper": "oidc-usermodel-attribute-mapper",
          "consentRequired": false,
          "config": {
            "introspection.token.claim": "true",
            "userinfo.token.claim": "true",
            "user.attribute": "profile",
            "id.token.claim": "true",
            "access.token.claim": "true",
            "claim.name": "profile",
            "jsonType.label": "String"
          }
        },
        {
          "id": "7dedfba4-6cf9-4e35-81f7-5737a178e1f1",
          "name": "username",
          "protocol": "openid-connect",
          "protocolMapper": "oidc-usermodel-attribute-mapper",
          "consentRequired": false,
          "config": {
            "introspection.token.claim": "true",
            "userinfo.token.claim": "true",
            "user.attribute": "username",
            "id.token.claim": "true",
            "access.token.claim": "true",
            "claim.name": "preferred_username",
            "jsonType.label": "String"
          }
        },
        {
          "id": "775f184a-77a8-4430-9180-6b6933dd250f",
          "name": "website",
          "protocol": "openid-connect",
          "protocolMapper": "oidc-usermodel-attribute-mapper",
          "consentRequired": false,
          "config": {
            "introspection.token.claim": "true",
            "userinfo.token.claim": "true",
            "user.attribute": "website",
            "id.token.claim": "true",
            "access.token.claim": "true",
            "claim.name": "website",
            "jsonType.label": "String"
          }
        },
        {
          "id": "d7dc2fa7-db50-489a-8691-fc1149f50281",
          "name": "middle name",
          "protocol": "openid-connect",
          "protocolMapper": "oidc-usermodel-attribute-mapper",
          "consentRequired": false,
          "config": {
            "introspection.token.claim": "true",
            "userinfo.token.claim": "true",
            "user.attribute": "middleName",
            "id.token.claim": "true",
            "access.token.claim": "true",
            "claim.name": "middle_name",
            "jsonType.label": "String"
          }
        },
        {
          "id": "f65c2e6f-4dfb-41c1-8cd9-1066ce215054",
          "name": "full name",
          "protocol": "openid-connect",
          "protocolMapper": "oidc-full-name-mapper",
          "consentRequired": false,
          "config": {
            "id.token.claim": "true",
            "introspection.token.claim": "true",
            "access.token.claim": "true",
            "userinfo.token.claim": "true"
          }
        },
        {
          "id": "64f51b14-fd5c-43a6-a633-172b010bcb1c",
          "name": "nickname",
          "protocol": "openid-connect",
          "protocolMapper": "oidc-usermodel-attribute-mapper",
          "consentRequired": false,
          "config": {
            "introspection.token.claim": "true",
            "userinfo.token.claim": "true",
            "user.attribute": "nickname",
            "id.token.claim": "true",
            "access.token.claim": "true",
            "claim.name": "nickname",
            "jsonType.label": "String"
          }
        },
        {
          "id": "8588e16a-b4ac-4fd3-9b12-6d37b3f43ae4",
          "name": "family name",
          "protocol": "openid-connect",
          "protocolMapper": "oidc-usermodel-attribute-mapper",
          "consentRequired": false,
          "config": {
            "introspection.token.claim": "true",
            "userinfo.token.claim": "true",
            "user.attribute": "lastName",
            "id.token.claim": "true",
            "access.token.claim": "true",
            "claim.name": "family_name",
            "jsonType.label": "String"
          }
        },
        {
          "id": "3d77002c-bb70-4e03-b662-033f70c24e16",
          "name": "given name",
          "protocol": "openid-connect",
          "protocolMapper": "oidc-usermodel-attribute-mapper",
          "consentRequired": false,
          "config": {
            "introspection.token.claim": "true",
            "userinfo.token.claim": "true",
            "user.attribute": "firstName",
            "id.token.claim": "true",
            "access.token.claim": "true",
            "claim.name": "given_name",
            "jsonType.label": "String"
          }
        },
        {
          "id": "6848746a-2ed1-47ba-a671-c05a1c6b731f",
          "name": "locale",
          "protocol": "openid-connect",
          "protocolMapper": "oidc-usermodel-attribute-mapper",
          "consentRequired": false,
          "config": {
            "introspection.token.claim": "true",
            "userinfo.token.claim": "true",
            "user.attribute": "locale",
            "id.token.claim": "true",
            "access.token.claim": "true",
            "claim.name": "locale",
            "jsonType.label": "String"
          }
        },
        {
          "id": "f52a8b08-fb12-4b55-9323-cb5d10fda800",
          "name": "birthdate",
          "protocol": "openid-connect",
          "protocolMapper": "oidc-usermodel-attribute-mapper",
          "consentRequired": false,
          "config": {
            "introspection.token.claim": "true",
            "userinfo.token.claim": "true",
            "user.attribute": "birthdate",
            "id.token.claim": "true",
            "access.token.claim": "true",
            "claim.name": "birthdate",
            "jsonType.label": "String"
          }
        },
        {
          "id": "d7cd49da-59da-43bc-bfca-a570f126ac4f",
          "name": "zoneinfo",
          "protocol": "openid-connect",
          "protocolMapper": "oidc-usermodel-attribute-mapper",
          "consentRequired": false,
          "config": {
            "introspection.token.claim": "true",
            "userinfo.token.claim": "true",
            "user.attribute": "zoneinfo",
            "id.token.claim": "true",
            "access.token.claim": "true",
            "claim.name": "zoneinfo",
            "jsonType.label": "String"
          }
        },
        {
          "id": "36a43800-26d6-4cdb-bb39-16c1127c06e9",
          "name": "gender",
          "protocol": "openid-connect",
          "protocolMapper": "oidc-usermodel-attribute-mapper",
          "consentRequired": false,
          "config": {
            "introspection.token.claim": "true",
            "userinfo.token.claim": "true",
            "user.attribute": "gender",
            "id.token.claim": "true",
            "access.token.claim": "true",
            "claim.name": "gender",
            "jsonType.label": "String"
          }
        },
        {
          "id": "8221c1e1-01ed-4a1c-b081-98f2f498ac7b",
          "name": "updated at",
          "protocol": "openid-connect",
          "protocolMapper": "oidc-usermodel-attribute-mapper",
          "consentRequired": false,
          "config": {
            "introspection.token.claim": "true",
            "userinfo.token.claim": "true",
            "user.attribute": "updatedAt",
            "id.token.claim": "true",
            "access.token.claim": "true",
            "claim.name": "updated_at",
            "jsonType.label": "long"
          }
        }
      ]
    },
    {
      "id": "703b83e9-8dd2-459f-afe2-3e39016c955d",
      "name": "basic",
      "description": "OpenID Connect scope for add all basic claims to the token",
      "protocol": "openid-connect",
      "attributes": {
        "include.in.token.scope": "false",
        "display.on.consent.screen": "false"
      },
      "protocolMappers": [
        {
          "id": "ca9152cc-6da1-4d8e-b395-74a612f327f5",
          "name": "sub",
          "protocol": "openid-connect",
          "protocolMapper": "oidc-sub-mapper",
          "consentRequired": false,
          "config": {
            "introspection.token.claim": "true",
            "access.token.claim": "true"
          }
        },
        {
          "id": "056bdac3-40d4-4b9b-9af2-003687fde2ce",
          "name": "auth_time",
          "protocol": "openid-connect",
          "protocolMapper": "oidc-usersessionmodel-note-mapper",
          "consentRequired": false,
          "config": {
            "user.session.note": "AUTH_TIME",
            "id.token.claim": "true",
            "introspection.token.claim": "true",
            "access.token.claim": "true",
            "claim.name": "auth_time",
            "jsonType.label": "long"
          }
        }
      ]
    },
    {
      "id": "29603962-aafc-49b7-a931-cd6fa4b2598d",
      "name": "offline_access",
      "description": "OpenID Connect built-in scope: offline_access",
      "protocol": "openid-connect",
      "attributes": {
        "consent.screen.text": "${offlineAccessScopeConsentText}",
        "display.on.consent.screen": "true"
      }
    },
    {
      "id": "7fa532f3-082d-4d0c-9558-9c46babde17e",
      "name": "email",
      "description": "OpenID Connect built-in scope: email",
      "protocol": "openid-connect",
      "attributes": {
        "include.in.token.scope": "true",
        "consent.screen.text": "${emailScopeConsentText}",
        "display.on.consent.screen": "true"
      },
      "protocolMappers": [
        {
          "id": "ea2c1e79-2fdd-463d-baa6-5054643dbe9c",
          "name": "email verified",
          "protocol": "openid-connect",
          "protocolMapper": "oidc-usermodel-property-mapper",
          "consentRequired": false,
          "config": {
            "introspection.token.claim": "true",
            "userinfo.token.claim": "true",
            "user.attribute": "emailVerified",
            "id.token.claim": "true",
            "access.token.claim": "true",
            "claim.name": "email_verified",
            "jsonType.label": "boolean"
          }
        },
        {
          "id": "7ff4c013-8de1-47b3-8e9e-66ae7996c3f6",
          "name": "email",
          "protocol": "openid-connect",
          "protocolMapper": "oidc-usermodel-attribute-mapper",
          "consentRequired": false,
          "config": {
            "introspection.token.claim": "true",
            "userinfo.token.claim": "true",
            "user.attribute": "email",
            "id.token.claim": "true",
            "access.token.claim": "true",
            "claim.name": "email",
            "jsonType.label": "String"
          }
        }
      ]
    },
    {
      "id": "a907b37b-7b78-45b8-b668-6c9b834691f0",
      "name": "address",
      "description": "OpenID Connect built-in scope: address",
      "protocol": "openid-connect",
      "attributes": {
        "include.in.token.scope": "true",
        "consent.screen.text": "${addressScopeConsentText}",
        "display.on.consent.screen": "true"
      },
      "protocolMappers": [
        {
          "id": "2c138740-62e2-4247-9821-0bd0c11c3cc5",
          "name": "address",
          "protocol": "openid-connect",
          "protocolMapper": "oidc-address-mapper",
          "consentRequired": false,
          "config": {
            "user.attribute.formatted": "formatted",
            "user.attribute.country": "country",
            "introspection.token.claim": "true",
            "user.attribute.postal_code": "postal_code",
            "userinfo.token.claim": "true",
            "user.attribute.street": "street",
            "id.token.claim": "true",
            "user.attribute.region": "region",
            "access.token.claim": "true",
            "user.attribute.locality": "locality"
          }
        }
      ]
    },
    {
      "id": "57090efa-f0f1-4149-b0d4-a6c1aa34eb7a",
      "name": "role_list",
      "description": "SAML role list",
      "protocol": "saml",
      "attributes": {
        "consent.screen.text": "${samlRoleListScopeConsentText}",
        "display.on.consent.screen": "true"
      },
      "protocolMappers": [
        {
          "id": "7ff9dd84-4541-430a-9fe2-cebe3bd97b52",
          "name": "role list",
          "protocol": "saml",
          "protocolMapper": "saml-role-list-mapper",
          "consentRequired": false,
          "config": {
            "single": "false",
            "attribute.nameformat": "Basic",
            "attribute.name": "Role"
          }
        }
      ]
    },
    {
      "id": "7be31786-99cf-4b84-9e3c-98889cf43e6e",
      "name": "phone",
      "description": "OpenID Connect built-in scope: phone",
      "protocol": "openid-connect",
      "attributes": {
        "include.in.token.scope": "true",
        "consent.screen.text": "${phoneScopeConsentText}",
        "display.on.consent.screen": "true"
      },
      "protocolMappers": [
        {
          "id": "8dcb327b-3dbf-4be8-9104-cef967099cee",
          "name": "phone number",
          "protocol": "openid-connect",
          "protocolMapper": "oidc-usermodel-attribute-mapper",
          "consentRequired": false,
          "config": {
            "introspection.token.claim": "true",
            "userinfo.token.claim": "true",
            "user.attribute": "phoneNumber",
            "id.token.claim": "true",
            "access.token.claim": "true",
            "claim.name": "phone_number",
            "jsonType.label": "String"
          }
        },
        {
          "id": "dff033f6-3751-4a7c-80a7-87d1ca9319b2",
          "name": "phone number verified",
          "protocol": "openid-connect",
          "protocolMapper": "oidc-usermodel-attribute-mapper",
          "consentRequired": false,
          "config": {
            "introspection.token.claim": "true",
            "userinfo.token.claim": "true",
            "user.attribute": "phoneNumberVerified",
            "id.token.claim": "true",
            "access.token.claim": "true",
            "claim.name": "phone_number_verified",
            "jsonType.label": "boolean"
          }
        }
      ]
    },
    {
      "id": "4d5b991c-11ed-4de6-83c0-496e06da29ba",
      "name": "roles",
      "description": "OpenID Connect scope for add user roles to the access token",
      "protocol": "openid-connect",
      "attributes": {
        "include.in.token.scope": "false",
        "consent.screen.text": "${rolesScopeConsentText}",
        "display.on.consent.screen": "true"
      },
      "protocolMappers": [
        {
          "id": "882cbc25-be89-41d6-8f01-4fab01ff46ca",
          "name": "audience resolve",
          "protocol": "openid-connect",
          "protocolMapper": "oidc-audience-resolve-mapper",
          "consentRequired": false,
          "config": {
            "introspection.token.claim": "true",
            "access.token.claim": "true"
          }
        },
        {
          "id": "e2ba4199-3a63-4979-8259-4842a2e760cb",
          "name": "client roles",
          "protocol": "openid-connect",
          "protocolMapper": "oidc-usermodel-client-role-mapper",
          "consentRequired": false,
          "config": {
            "user.attribute": "foo",
            "introspection.token.claim": "true",
            "access.token.claim": "true",
            "claim.name": "resource_access.${client_id}.roles",
            "jsonType.label": "String",
            "multivalued": "true"
          }
        },
        {
          "id": "795b371b-5a1a-4b18-b494-83e93ff1809c",
          "name": "realm roles",
          "protocol": "openid-connect",
          "protocolMapper": "oidc-usermodel-realm-role-mapper",
          "consentRequired": false,
          "config": {
            "user.attribute": "foo",
            "introspection.token.claim": "true",
            "access.token.claim": "true",
            "claim.name": "realm_access.roles",
            "jsonType.label": "String",
            "multivalued": "true"
          }
        }
      ]
    },
    {
      "id": "38e78c7b-8d72-45f2-81fe-3fd241d873d1",
      "name": "organization",
      "description": "Additional claims about the organization a subject belongs to",
      "protocol": "openid-connect",
      "attributes": {
        "include.in.token.scope": "true",
        "consent.screen.text": "${organizationScopeConsentText}",
        "display.on.consent.screen": "true"
      },
      "protocolMappers": [
        {
          "id": "61d20430-6b3b-448a-9dc4-e63fb2b34a09",
          "name": "organization",
          "protocol": "openid-connect",
          "protocolMapper": "oidc-organization-membership-mapper",
          "consentRequired": false,
          "config": {
            "id.token.claim": "true",
            "introspection.token.claim": "true",
            "access.token.claim": "true",
            "claim.name": "organization",
            "jsonType.label": "String",
            "multivalued": "true"
          }
        }
      ]
    },
    {
      "id": "00ce1bc2-df10-43a7-8df0-2d77b606764f",
      "name": "saml_organization",
      "description": "Organization Membership",
      "protocol": "saml",
      "attributes": {
        "display.on.consent.screen": "false"
      },
      "protocolMappers": [
        {
          "id": "1a0e73a3-ece2-421b-8e77-e7cebde51911",
          "name": "organization",
          "protocol": "saml",
          "protocolMapper": "saml-organization-membership-mapper",
          "consentRequired": false,
          "config": {}
        }
      ]
    },
    {
      "id": "03d126e1-48da-4713-852a-b6f3107dc0cc",
      "name": "microprofile-jwt",
      "description": "Microprofile - JWT built-in scope",
      "protocol": "openid-connect",
      "attributes": {
        "include.in.token.scope": "true",
        "display.on.consent.screen": "false"
      },
      "protocolMappers": [
        {
          "id": "bc9c37a6-4f06-4cc9-83b0-19d1fda71ab8",
          "name": "groups",
          "protocol": "openid-connect",
          "protocolMapper": "oidc-usermodel-realm-role-mapper",
          "consentRequired": false,
          "config": {
            "introspection.token.claim": "true",
            "multivalued": "true",
            "user.attribute": "foo",
            "id.token.claim": "true",
            "access.token.claim": "true",
            "claim.name": "groups",
            "jsonType.label": "String"
          }
        },
        {
          "id": "23094f21-0c42-4dfd-baae-2d6e4d9f5784",
          "name": "upn",
          "protocol": "openid-connect",
          "protocolMapper": "oidc-usermodel-attribute-mapper",
          "consentRequired": false,
          "config": {
            "introspection.token.claim": "true",
            "userinfo.token.claim": "true",
            "user.attribute": "username",
            "id.token.claim": "true",
            "access.token.claim": "true",
            "claim.name": "upn",
            "jsonType.label": "String"
          }
        }
      ]
    },
    {
      "id": "077f8667-2bc1-4661-ba81-936f243f9f2b",
      "name": "acr",
      "description": "OpenID Connect scope for add acr (authentication context class reference) to the token",
      "protocol": "openid-connect",
      "attributes": {
        "include.in.token.scope": "false",
        "display.on.consent.screen": "false"
      },
      "protocolMappers": [
        {
          "id": "66cbd572-4418-439c-ac99-d9ceb79b220d",
          "name": "acr loa level",
          "protocol": "openid-connect",
          "protocolMapper": "oidc-acr-mapper",
          "consentRequired": false,
          "config": {
            "id.token.claim": "true",
            "access.token.claim": "true",
            "introspection.token.claim": "true"
          }
        }
      ]
    },
    {
      "id": "6c960a18-45a4-447a-b16c-57b080aa82d9",
      "name": "web-origins",
      "description": "OpenID Connect scope for add allowed web origins to the access token",
      "protocol": "openid-connect",
      "attributes": {
        "include.in.token.scope": "false",
        "consent.screen.text": "",
        "display.on.consent.screen": "false"
      },
      "protocolMappers": [
        {
          "id": "e5197ee8-dbb4-4871-9832-c15fbe2a5d3a",
          "name": "allowed web origins",
          "protocol": "openid-connect",
          "protocolMapper": "oidc-allowed-origins-mapper",
          "consentRequired": false,
          "config": {
            "access.token.claim": "true",
            "introspection.token.claim": "true"
          }
        }
      ]
    }
  ],
  "defaultDefaultClientScopes": [
    "role_list",
    "saml_organization",
    "profile",
    "email",
    "roles",
    "web-origins",
    "acr",
    "basic"
  ],
  "defaultOptionalClientScopes": [
    "offline_access",
    "address",
    "phone",
    "microprofile-jwt",
    "organization"
  ],
  "browserSecurityHeaders": {
    "contentSecurityPolicyReportOnly": "",
    "xContentTypeOptions": "nosniff",
    "referrerPolicy": "no-referrer",
    "xRobotsTag": "none",
    "xFrameOptions": "SAMEORIGIN",
    "contentSecurityPolicy": "frame-src 'self'; frame-ancestors 'self'; object-src 'none';",
    "xXSSProtection": "1; mode=block",
    "strictTransportSecurity": "max-age=31536000; includeSubDomains"
  },
  "smtpServer": {},
  "eventsEnabled": false,
  "eventsListeners": [
    "jboss-logging"
  ],
  "enabledEventTypes": [],
  "adminEventsEnabled": false,
  "adminEventsDetailsEnabled": false,
  "identityProviders": [],
  "identityProviderMappers": [],
  "components": {
    "org.keycloak.services.clientregistration.policy.ClientRegistrationPolicy": [
      {
        "id": "235e5ec0-90ab-466a-acc3-1bcc6699fe3a",
        "name": "Allowed Client Scopes",
        "providerId": "allowed-client-templates",
        "subType": "authenticated",
        "subComponents": {},
        "config": {
          "allow-default-scopes": [
            "true"
          ]
        }
      },
      {
        "id": "3132a18a-60a4-4656-9b9f-5866ee3c6646",
        "name": "Consent Required",
        "providerId": "consent-required",
        "subType": "anonymous",
        "subComponents": {},
        "config": {}
      },
      {
        "id": "e6f5ad87-bee3-4d8d-b52d-099f6d295e03",
        "name": "Allowed Client Scopes",
        "providerId": "allowed-client-templates",
        "subType": "anonymous",
        "subComponents": {},
        "config": {
          "allow-default-scopes": [
            "true"
          ]
        }
      },
      {
        "id": "2de939f4-a77c-4785-9d1b-b3d25808ba5c",
        "name": "Trusted Hosts",
        "providerId": "trusted-hosts",
        "subType": "anonymous",
        "subComponents": {},
        "config": {
          "host-sending-registration-request-must-match": [
            "true"
          ],
          "client-uris-must-match": [
            "true"
          ]
        }
      },
      {
        "id": "73c29969-0306-43bd-8df5-42a6246dceb6",
        "name": "Full Scope Disabled",
        "providerId": "scope",
        "subType": "anonymous",
        "subComponents": {},
        "config": {}
      },
      {
        "id": "a46ce1e9-5024-4693-affa-b3237ff1e616",
        "name": "Allowed Protocol Mapper Types",
        "providerId": "allowed-protocol-mappers",
        "subType": "anonymous",
        "subComponents": {},
        "config": {
          "allowed-protocol-mapper-types": [
            "saml-user-property-mapper",
            "oidc-usermodel-property-mapper",
            "oidc-address-mapper",
            "oidc-sha256-pairwise-sub-mapper",
            "saml-role-list-mapper",
            "saml-user-attribute-mapper",
            "oidc-full-name-mapper",
            "oidc-usermodel-attribute-mapper"
          ]
        }
      },
      {
        "id": "660abef0-5166-46eb-a3b0-9b7c2845d88a",
        "name": "Max Clients Limit",
        "providerId": "max-clients",
        "subType": "anonymous",
        "subComponents": {},
        "config": {
          "max-clients": [
            "200"
          ]
        }
      },
      {
        "id": "a70b3721-b7fe-40cb-b8fe-25ebb063a0cd",
        "name": "Allowed Protocol Mapper Types",
        "providerId": "allowed-protocol-mappers",
        "subType": "authenticated",
        "subComponents": {},
        "config": {
          "allowed-protocol-mapper-types": [
            "oidc-usermodel-property-mapper",
            "oidc-address-mapper",
            "oidc-sha256-pairwise-sub-mapper",
            "saml-user-property-mapper",
            "oidc-usermodel-attribute-mapper",
            "saml-role-list-mapper",
            "saml-user-attribute-mapper",
            "oidc-full-name-mapper"
          ]
        }
      }
    ],
    "org.keycloak.keys.KeyProvider": [
      {
        "id": "468e5b25-736e-4bec-927f-4813bf8f9987",
        "name": "aes-generated",
        "providerId": "aes-generated",
        "subComponents": {},
        "config": {
          "priority": [
            "100"
          ]
        }
      },
      {
        "id": "e6f4fd92-48d1-4e51-a880-1c0d3e4ab1d1",
        "name": "rsa-enc-generated",
        "providerId": "rsa-enc-generated",
        "subComponents": {},
        "config": {
          "priority": [
            "100"
          ],
          "algorithm": [
            "RSA-OAEP"
          ]
        }
      },
      {
        "id": "addf367f-13ed-487a-a315-0adcc23c802a",
        "name": "hmac-generated-hs512",
        "providerId": "hmac-generated",
        "subComponents": {},
        "config": {
          "priority": [
            "100"
          ],
          "algorithm": [
            "HS512"
          ]
        }
      },
      {
        "id": "55ab734c-a455-4265-a65b-8f93f777ba50",
        "name": "rsa-generated",
        "providerId": "rsa-generated",
        "subComponents": {},
        "config": {
          "priority": [
            "100"
          ]
        }
      }
    ]
  },
  "internationalizationEnabled": false,
  "supportedLocales": [],
  "authenticationFlows": [
    {
      "id": "afb95041-cd1e-4ccb-8be1-17e62ec8d267",
      "alias": "Account verification options",
      "description": "Method with which to verity the existing account",
      "providerId": "basic-flow",
      "topLevel": false,
      "builtIn": true,
      "authenticationExecutions": [
        {
          "authenticator": "idp-email-verification",
          "authenticatorFlow": false,
          "requirement": "ALTERNATIVE",
          "priority": 10,
          "autheticatorFlow": false,
          "userSetupAllowed": false
        },
        {
          "authenticatorFlow": true,
          "requirement": "ALTERNATIVE",
          "priority": 20,
          "autheticatorFlow": true,
          "flowAlias": "Verify Existing Account by Re-authentication",
          "userSetupAllowed": false
        }
      ]
    },
    {
      "id": "75ac58db-5948-420f-89a8-146dcec0610a",
      "alias": "Browser - Conditional OTP",
      "description": "Flow to determine if the OTP is required for the authentication",
      "providerId": "basic-flow",
      "topLevel": false,
      "builtIn": true,
      "authenticationExecutions": [
        {
          "authenticator": "conditional-user-configured",
          "authenticatorFlow": false,
          "requirement": "REQUIRED",
          "priority": 10,
          "autheticatorFlow": false,
          "userSetupAllowed": false
        },
        {
          "authenticator": "auth-otp-form",
          "authenticatorFlow": false,
          "requirement": "REQUIRED",
          "priority": 20,
          "autheticatorFlow": false,
          "userSetupAllowed": false
        }
      ]
    },
    {
      "id": "aa91b119-40e5-49e2-b01e-005f92a44834",
      "alias": "Browser - Conditional Organization",
      "description": "Flow to determine if the organization identity-first login is to be used",
      "providerId": "basic-flow",
      "topLevel": false,
      "builtIn": true,
      "authenticationExecutions": [
        {
          "authenticator": "conditional-user-configured",
          "authenticatorFlow": false,
          "requirement": "REQUIRED",
          "priority": 10,
          "autheticatorFlow": false,
          "userSetupAllowed": false
        },
        {
          "authenticator": "organization",
          "authenticatorFlow": false,
          "requirement": "ALTERNATIVE",
          "priority": 20,
          "autheticatorFlow": false,
          "userSetupAllowed": false
        }
      ]
    },
    {
      "id": "2db65e22-63d9-4440-a33a-0d03f5410c38",
      "alias": "Direct Grant - Conditional OTP",
      "description": "Flow to determine if the OTP is required for the authentication",
      "providerId": "basic-flow",
      "topLevel": false,
      "builtIn": true,
      "authenticationExecutions": [
        {
          "authenticator": "conditional-user-configured",
          "authenticatorFlow": false,
          "requirement": "REQUIRED",
          "priority": 10,
          "autheticatorFlow": false,
          "userSetupAllowed": false
        },
        {
          "authenticator": "direct-grant-validate-otp",
          "authenticatorFlow": false,
          "requirement": "REQUIRED",
          "priority": 20,
          "autheticatorFlow": false,
          "userSetupAllowed": false
        }
      ]
    },
    {
      "id": "96a0c10b-a0c5-49a0-83b9-a57791b214ce",
      "alias": "First Broker Login - Conditional Organization",
      "description": "Flow to determine if the authenticator that adds organization members is to be used",
      "providerId": "basic-flow",
      "topLevel": false,
      "builtIn": true,
      "authenticationExecutions": [
        {
          "authenticator": "conditional-user-configured",
          "authenticatorFlow": false,
          "requirement": "REQUIRED",
          "priority": 10,
          "autheticatorFlow": false,
          "userSetupAllowed": false
        },
        {
          "authenticator": "idp-add-organization-member",
          "authenticatorFlow": false,
          "requirement": "REQUIRED",
          "priority": 20,
          "autheticatorFlow": false,
          "userSetupAllowed": false
        }
      ]
    },
    {
      "id": "ff417655-df6d-466b-acbe-45fa194ac981",
      "alias": "First broker login - Conditional OTP",
      "description": "Flow to determine if the OTP is required for the authentication",
      "providerId": "basic-flow",
      "topLevel": false,
      "builtIn": true,
      "authenticationExecutions": [
        {
          "authenticator": "conditional-user-configured",
          "authenticatorFlow": false,
          "requirement": "REQUIRED",
          "priority": 10,
          "autheticatorFlow": false,
          "userSetupAllowed": false
        },
        {
          "authenticator": "auth-otp-form",
          "authenticatorFlow": false,
          "requirement": "REQUIRED",
          "priority": 20,
          "autheticatorFlow": false,
          "userSetupAllowed": false
        }
      ]
    },
    {
      "id": "e527e925-841d-4d1e-8fa3-472a57dfc658",
      "alias": "Handle Existing Account",
      "description": "Handle what to do if there is existing account with same email/username like authenticated identity provider",
      "providerId": "basic-flow",
      "topLevel": false,
      "builtIn": true,
      "authenticationExecutions": [
        {
          "authenticator": "idp-confirm-link",
          "authenticatorFlow": false,
          "requirement": "REQUIRED",
          "priority": 10,
          "autheticatorFlow": false,
          "userSetupAllowed": false
        },
        {
          "authenticatorFlow": true,
          "requirement": "REQUIRED",
          "priority": 20,
          "autheticatorFlow": true,
          "flowAlias": "Account verification options",
          "userSetupAllowed": false
        }
      ]
    },
    {
      "id": "661619c6-7a4a-47ce-9825-3f451cc364c9",
      "alias": "Organization",
      "providerId": "basic-flow",
      "topLevel": false,
      "builtIn": true,
      "authenticationExecutions": [
        {
          "authenticatorFlow": true,
          "requirement": "CONDITIONAL",
          "priority": 10,
          "autheticatorFlow": true,
          "flowAlias": "Browser - Conditional Organization",
          "userSetupAllowed": false
        }
      ]
    },
    {
      "id": "8947fc1f-5659-4ac3-b3d9-438d2387484a",
      "alias": "Reset - Conditional OTP",
      "description": "Flow to determine if the OTP should be reset or not. Set to REQUIRED to force.",
      "providerId": "basic-flow",
      "topLevel": false,
      "builtIn": true,
      "authenticationExecutions": [
        {
          "authenticator": "conditional-user-configured",
          "authenticatorFlow": false,
          "requirement": "REQUIRED",
          "priority": 10,
          "autheticatorFlow": false,
          "userSetupAllowed": false
        },
        {
          "authenticator": "reset-otp",
          "authenticatorFlow": false,
          "requirement": "REQUIRED",
          "priority": 20,
          "autheticatorFlow": false,
          "userSetupAllowed": false
        }
      ]
    },
    {
      "id": "b02c78d3-e753-4c64-8c07-369283f87061",
      "alias": "User creation or linking",
      "description": "Flow for the existing/non-existing user alternatives",
      "providerId": "basic-flow",
      "topLevel": false,
      "builtIn": true,
      "authenticationExecutions": [
        {
          "authenticatorConfig": "create unique user config",
          "authenticator": "idp-create-user-if-unique",
          "authenticatorFlow": false,
          "requirement": "ALTERNATIVE",
          "priority": 10,
          "autheticatorFlow": false,
          "userSetupAllowed": false
        },
        {
          "authenticatorFlow": true,
          "requirement": "ALTERNATIVE",
          "priority": 20,
          "autheticatorFlow": true,
          "flowAlias": "Handle Existing Account",
          "userSetupAllowed": false
        }
      ]
    },
    {
      "id": "5020d8dc-4a32-4df9-9782-41ebc97a7860",
      "alias": "Verify Existing Account by Re-authentication",
      "description": "Reauthentication of existing account",
      "providerId": "basic-flow",
      "topLevel": false,
      "builtIn": true,
      "authenticationExecutions": [
        {
          "authenticator": "idp-username-password-form",
          "authenticatorFlow": false,
          "requirement": "REQUIRED",
          "priority": 10,
          "autheticatorFlow": false,
          "userSetupAllowed": false
        },
        {
          "authenticatorFlow": true,
          "requirement": "CONDITIONAL",
          "priority": 20,
          "autheticatorFlow": true,
          "flowAlias": "First broker login - Conditional OTP",
          "userSetupAllowed": false
        }
      ]
    },
    {
      "id": "c8cd230b-108d-45bd-8ea8-c51bde8d1baa",
      "alias": "browser",
      "description": "Browser based authentication",
      "providerId": "basic-flow",
      "topLevel": true,
      "builtIn": true,
      "authenticationExecutions": [
        {
          "authenticator": "auth-cookie",
          "authenticatorFlow": false,
          "requirement": "ALTERNATIVE",
          "priority": 10,
          "autheticatorFlow": false,
          "userSetupAllowed": false
        },
        {
          "authenticator": "auth-spnego",
          "authenticatorFlow": false,
          "requirement": "DISABLED",
          "priority": 20,
          "autheticatorFlow": false,
          "userSetupAllowed": false
        },
        {
          "authenticator": "identity-provider-redirector",
          "authenticatorFlow": false,
          "requirement": "ALTERNATIVE",
          "priority": 25,
          "autheticatorFlow": false,
          "userSetupAllowed": false
        },
        {
          "authenticatorFlow": true,
          "requirement": "ALTERNATIVE",
          "priority": 26,
          "autheticatorFlow": true,
          "flowAlias": "Organization",
          "userSetupAllowed": false
        },
        {
          "authenticatorFlow": true,
          "requirement": "ALTERNATIVE",
          "priority": 30,
          "autheticatorFlow": true,
          "flowAlias": "forms",
          "userSetupAllowed": false
        }
      ]
    },
    {
      "id": "81b64ed6-bc04-4589-998b-83f30b149b91",
      "alias": "clients",
      "description": "Base authentication for clients",
      "providerId": "client-flow",
      "topLevel": true,
      "builtIn": true,
      "authenticationExecutions": [
        {
          "authenticator": "client-secret",
          "authenticatorFlow": false,
          "requirement": "ALTERNATIVE",
          "priority": 10,
          "autheticatorFlow": false,
          "userSetupAllowed": false
        },
        {
          "authenticator": "client-jwt",
          "authenticatorFlow": false,
          "requirement": "ALTERNATIVE",
          "priority": 20,
          "autheticatorFlow": false,
          "userSetupAllowed": false
        },
        {
          "authenticator": "client-secret-jwt",
          "authenticatorFlow": false,
          "requirement": "ALTERNATIVE",
          "priority": 30,
          "autheticatorFlow": false,
          "userSetupAllowed": false
        },
        {
          "authenticator": "client-x509",
          "authenticatorFlow": false,
          "requirement": "ALTERNATIVE",
          "priority": 40,
          "autheticatorFlow": false,
          "userSetupAllowed": false
        }
      ]
    },
    {
      "id": "a947f34d-1c51-4c2a-b6bd-d5ec79c730f4",
      "alias": "direct grant",
      "description": "OpenID Connect Resource Owner Grant",
      "providerId": "basic-flow",
      "topLevel": true,
      "builtIn": true,
      "authenticationExecutions": [
        {
          "authenticator": "direct-grant-validate-username",
          "authenticatorFlow": false,
          "requirement": "REQUIRED",
          "priority": 10,
          "autheticatorFlow": false,
          "userSetupAllowed": false
        },
        {
          "authenticator": "direct-grant-validate-password",
          "authenticatorFlow": false,
          "requirement": "REQUIRED",
          "priority": 20,
          "autheticatorFlow": false,
          "userSetupAllowed": false
        },
        {
          "authenticatorFlow": true,
          "requirement": "CONDITIONAL",
          "priority": 30,
          "autheticatorFlow": true,
          "flowAlias": "Direct Grant - Conditional OTP",
          "userSetupAllowed": false
        }
      ]
    },
    {
      "id": "8bbda5be-c79f-4e34-ab80-9979a41bb0cd",
      "alias": "docker auth",
      "description": "Used by Docker clients to authenticate against the IDP",
      "providerId": "basic-flow",
      "topLevel": true,
      "builtIn": true,
      "authenticationExecutions": [
        {
          "authenticator": "docker-http-basic-authenticator",
          "authenticatorFlow": false,
          "requirement": "REQUIRED",
          "priority": 10,
          "autheticatorFlow": false,
          "userSetupAllowed": false
        }
      ]
    },
    {
      "id": "aa2bc913-ce9f-4cf4-8045-52a6dd93f0e5",
      "alias": "first broker login",
      "description": "Actions taken after first broker login with identity provider account, which is not yet linked to any Keycloak account",
      "providerId": "basic-flow",
      "topLevel": true,
      "builtIn": true,
      "authenticationExecutions": [
        {
          "authenticatorConfig": "review profile config",
          "authenticator": "idp-review-profile",
          "authenticatorFlow": false,
          "requirement": "REQUIRED",
          "priority": 10,
          "autheticatorFlow": false,
          "userSetupAllowed": false
        },
        {
          "authenticatorFlow": true,
          "requirement": "REQUIRED",
          "priority": 20,
          "autheticatorFlow": true,
          "flowAlias": "User creation or linking",
          "userSetupAllowed": false
        },
        {
          "authenticatorFlow": true,
          "requirement": "CONDITIONAL",
          "priority": 50,
          "autheticatorFlow": true,
          "flowAlias": "First Broker Login - Conditional Organization",
          "userSetupAllowed": false
        }
      ]
    },
    {
      "id": "b15292f4-5769-46ac-8f64-106526b5f68b",
      "alias": "forms",
      "description": "Username, password, otp and other auth forms.",
      "providerId": "basic-flow",
      "topLevel": false,
      "builtIn": true,
      "authenticationExecutions": [
        {
          "authenticator": "auth-username-password-form",
          "authenticatorFlow": false,
          "requirement": "REQUIRED",
          "priority": 10,
          "autheticatorFlow": false,
          "userSetupAllowed": false
        },
        {
          "authenticatorFlow": true,
          "requirement": "CONDITIONAL",
          "priority": 20,
          "autheticatorFlow": true,
          "flowAlias": "Browser - Conditional OTP",
          "userSetupAllowed": false
        }
      ]
    },
    {
      "id": "610d6603-383a-4162-927f-d49a484b481c",
      "alias": "registration",
      "description": "Registration flow",
      "providerId": "basic-flow",
      "topLevel": true,
      "builtIn": true,
      "authenticationExecutions": [
        {
          "authenticator": "registration-page-form",
          "authenticatorFlow": true,
          "requirement": "REQUIRED",
          "priority": 10,
          "autheticatorFlow": true,
          "flowAlias": "registration form",
          "userSetupAllowed": false
        }
      ]
    },
    {
      "id": "ef1ccac4-51c3-413e-b21e-7a234dedf67f",
      "alias": "registration form",
      "description": "Registration form",
      "providerId": "form-flow",
      "topLevel": false,
      "builtIn": true,
      "authenticationExecutions": [
        {
          "authenticator": "registration-user-creation",
          "authenticatorFlow": false,
          "requirement": "REQUIRED",
          "priority": 20,
          "autheticatorFlow": false,
          "userSetupAllowed": false
        },
        {
          "authenticator": "registration-password-action",
          "authenticatorFlow": false,
          "requirement": "REQUIRED",
          "priority": 50,
          "autheticatorFlow": false,
          "userSetupAllowed": false
        },
        {
          "authenticator": "registration-recaptcha-action",
          "authenticatorFlow": false,
          "requirement": "DISABLED",
          "priority": 60,
          "autheticatorFlow": false,
          "userSetupAllowed": false
        },
        {
          "authenticator": "registration-terms-and-conditions",
          "authenticatorFlow": false,
          "requirement": "DISABLED",
          "priority": 70,
          "autheticatorFlow": false,
          "userSetupAllowed": false
        }
      ]
    },
    {
      "id": "f72ad50f-853f-4503-b1be-15a661b39d75",
      "alias": "reset credentials",
      "description": "Reset credentials for a user if they forgot their password or something",
      "providerId": "basic-flow",
      "topLevel": true,
      "builtIn": true,
      "authenticationExecutions": [
        {
          "authenticator": "reset-credentials-choose-user",
          "authenticatorFlow": false,
          "requirement": "REQUIRED",
          "priority": 10,
          "autheticatorFlow": false,
          "userSetupAllowed": false
        },
        {
          "authenticator": "reset-credential-email",
          "authenticatorFlow": false,
          "requirement": "REQUIRED",
          "priority": 20,
          "autheticatorFlow": false,
          "userSetupAllowed": false
        },
        {
          "authenticator": "reset-password",
          "authenticatorFlow": false,
          "requirement": "REQUIRED",
          "priority": 30,
          "autheticatorFlow": false,
          "userSetupAllowed": false
        },
        {
          "authenticatorFlow": true,
          "requirement": "CONDITIONAL",
          "priority": 40,
          "autheticatorFlow": true,
          "flowAlias": "Reset - Conditional OTP",
          "userSetupAllowed": false
        }
      ]
    },
    {
      "id": "288cb9dc-8287-4c6e-a6fa-87380954cf57",
      "alias": "saml ecp",
      "description": "SAML ECP Profile Authentication Flow",
      "providerId": "basic-flow",
      "topLevel": true,
      "builtIn": true,
      "authenticationExecutions": [
        {
          "authenticator": "http-basic-authenticator",
          "authenticatorFlow": false,
          "requirement": "REQUIRED",
          "priority": 10,
          "autheticatorFlow": false,
          "userSetupAllowed": false
        }
      ]
    }
  ],
  "authenticatorConfig": [
    {
      "id": "40c6f1bb-6624-4789-a3b5-76a367c6b367",
      "alias": "create unique user config",
      "config": {
        "require.password.update.after.registration": "false"
      }
    },
    {
      "id": "f641f262-c73e-40da-bd0e-4c34bfab53f6",
      "alias": "review profile config",
      "config": {
        "update.profile.on.first.login": "missing"
      }
    }
  ],
  "requiredActions": [
    {
      "alias": "CONFIGURE_TOTP",
      "name": "Configure OTP",
      "providerId": "CONFIGURE_TOTP",
      "enabled": true,
      "defaultAction": false,
      "priority": 10,
      "config": {}
    },
    {
      "alias": "TERMS_AND_CONDITIONS",
      "name": "Terms and Conditions",
      "providerId": "TERMS_AND_CONDITIONS",
      "enabled": false,
      "defaultAction": false,
      "priority": 20,
      "config": {}
    },
    {
      "alias": "UPDATE_PASSWORD",
      "name": "Update Password",
      "providerId": "UPDATE_PASSWORD",
      "enabled": true,
      "defaultAction": false,
      "priority": 30,
      "config": {}
    },
    {
      "alias": "UPDATE_PROFILE",
      "name": "Update Profile",
      "providerId": "UPDATE_PROFILE",
      "enabled": true,
      "defaultAction": false,
      "priority": 40,
      "config": {}
    },
    {
      "alias": "VERIFY_EMAIL",
      "name": "Verify Email",
      "providerId": "VERIFY_EMAIL",
      "enabled": true,
      "defaultAction": false,
      "priority": 50,
      "config": {}
    },
    {
      "alias": "delete_account",
      "name": "Delete Account",
      "providerId": "delete_account",
      "enabled": false,
      "defaultAction": false,
      "priority": 60,
      "config": {}
    },
    {
      "alias": "webauthn-register",
      "name": "Webauthn Register",
      "providerId": "webauthn-register",
      "enabled": true,
      "defaultAction": false,
      "priority": 70,
      "config": {}
    },
    {
      "alias": "webauthn-register-passwordless",
      "name": "Webauthn Register Passwordless",
      "providerId": "webauthn-register-passwordless",
      "enabled": true,
      "defaultAction": false,
      "priority": 80,
      "config": {}
    },
    {
      "alias": "VERIFY_PROFILE",
      "name": "Verify Profile",
      "providerId": "VERIFY_PROFILE",
      "enabled": true,
      "defaultAction": false,
      "priority": 90,
      "config": {}
    },
    {
      "alias": "delete_credential",
      "name": "Delete Credential",
      "providerId": "delete_credential",
      "enabled": true,
      "defaultAction": false,
      "priority": 100,
      "config": {}
    },
    {
      "alias": "update_user_locale",
      "name": "Update User Locale",
      "providerId": "update_user_locale",
      "enabled": true,
      "defaultAction": false,
      "priority": 1000,
      "config": {}
    }
  ],
  "browserFlow": "browser",
  "registrationFlow": "registration",
  "directGrantFlow": "direct grant",
  "resetCredentialsFlow": "reset credentials",
  "clientAuthenticationFlow": "clients",
  "dockerAuthenticationFlow": "docker auth",
  "firstBrokerLoginFlow": "first broker login",
  "attributes": {
    "cibaBackchannelTokenDeliveryMode": "poll",
    "cibaExpiresIn": "120",
    "cibaAuthRequestedUserHint": "login_hint",
    "oauth2DeviceCodeLifespan": "600",
    "oauth2DevicePollingInterval": "5",
    "parRequestUriLifespan": "60",
    "cibaInterval": "5",
    "realmReusableOtpCode": "false"
  },
  "keycloakVersion": "26.0.7",
  "userManagedAccessAllowed": false,
  "organizationsEnabled": false,
  "clientProfiles": {
    "profiles": []
  },
  "clientPolicies": {
    "policies": []
  }
}